.gitignore
HISTORY.rst
README.rst
setup.py
chance/__init__.py
chance/admin.py
chance/forms.py
chance/models.py
chance/signals.py
chance/slug_urls.py
chance/urls.py
chance/views.py
chance/migrations/0001_initial.py
chance/migrations/0002_add_eventchoice_allow_multiple.py
chance/migrations/0003_add_created_and_label.py
chance/migrations/0004_add_registration_owner.py
chance/migrations/0005_auto__add_talk.py
chance/migrations/0006_add_talk_title_index.py
chance/migrations/0007_add_transaction.py
chance/migrations/0008_add_scheduleitem_and_track.py
chance/migrations/0009_add_event_slug.py
chance/migrations/__init__.py
chance/templates/chance/event_detail.html
chance/templates/chance/event_list.html
chance/templates/chance/registration_email.txt
chance/templates/chance/registration_email_manager_subject.txt
chance/templates/chance/registration_email_subject.txt
chance/templates/chance/registration_form.html
django_chance.egg-info/PKG-INFO
django_chance.egg-info/SOURCES.txt
django_chance.egg-info/dependency_links.txt
django_chance.egg-info/not-zip-safe
django_chance.egg-info/requires.txt
django_chance.egg-info/top_level.txt