Metadata-Version: 1.1
Name: django-chance
Version: 0.4.1
Summary: Django CMS conference application
Home-page: https://github.com/pytexas/django-chance
Author: Benjamin Liles
Author-email: benliles@pytexas.net
License: UNKNOWN
Keywords: django cms plugin events conference
Platform: UNKNOWN
Classifier: Framework :: Django
Classifier: Development Status :: 4 - Beta
Classifier: Programming Language :: Python
Classifier: Topic :: Internet :: WWW/HTTP
Classifier: Topic :: Software Development :: Libraries :: Python Modules
Classifier: License :: OSI Approved :: Apache Software License
